[{"place_id": 230292905, "licence": "Data \u00a9 OpenStreetMap contributors, ODbL 1.0. http://osm.org/copyright", "osm_type": "node", "osm_id": 5696928866, "lat": "19.1196976", "lon": "72.8464205", "class": "railway", "type": "station", "place_rank": 30, "importance": 0.36467385585497514, "addresstype": "railway", "name": "Andheri", "display_name": "Andheri, Masjid Galli, Gaondevi Dongri, Andheri West, K/W Ward, Mumbai Zone 3, Mumbai, Mumbai Suburban District, Maharashtra, 400069, India", "boundingbox": ["19.1146976", "19.1246976", "72.8414205", "72.8514205"]}]